nkdfu/__init__.py
nkdfu/dfu.py
nkdfu/dfu_flash.py
nkdfu-0.2.dist-info/entry_points.txt
nkdfu-0.2.dist-info/LICENSE
nkdfu-0.2.dist-info/WHEEL
nkdfu-0.2.dist-info/METADATA
nkdfu-0.2.dist-info/RECORD
