Metadata-Version: 2.1
Name: nkdfu
Version: 0.2
Summary: DFU tool for updating Nitrokeys' firmware
Home-page: https://github.com/Nitrokey/nkdfu
Author: Nitrokey
Author-email: pypi@nitrokey.com
Requires-Python: >=3.6
Classifier: License :: OSI Approved :: GNU General Public License v2 (GPLv2)
Classifier: Intended Audience :: Developers
Classifier: Intended Audience :: End Users/Desktop
Classifier: Programming Language :: Python :: 3 :: Only
Classifier: Programming Language :: Python :: 3.6
Classifier: Programming Language :: Python :: 3.7
Requires-Dist: fire
Requires-Dist: tqdm
Requires-Dist: intelhex >= 2.3.0
Requires-Dist: libusb1 >= 1.9.3
